LICENSE
README.md
pyproject.toml
setup.cfg
setup.py
mysql_banner/__init__.py
mysql_banner/base.py
mysql_banner.egg-info/PKG-INFO
mysql_banner.egg-info/SOURCES.txt
mysql_banner.egg-info/dependency_links.txt
mysql_banner.egg-info/requires.txt
mysql_banner.egg-info/top_level.txt